emllib/__init__.py
emllib/dataclass/__init__.py
emllib/dataclass/eml220/__init__.py
emllib/dataclass/eml220/access.py
emllib/dataclass/eml220/access_rule.py
emllib/dataclass/eml220/access_rule_value.py
emllib/dataclass/eml220/access_type.py
emllib/dataclass/eml220/access_type_order.py
emllib/dataclass/eml220/accuracy.py
emllib/dataclass/eml220/action.py
emllib/dataclass/eml220/address.py
emllib/dataclass/eml220/angle_units.py
emllib/dataclass/eml220/annotation.py
emllib/dataclass/eml220/article.py
emllib/dataclass/eml220/attribute.py
emllib/dataclass/eml220/attribute_list.py
emllib/dataclass/eml220/attribute_type.py
emllib/dataclass/eml220/audio_visual.py
emllib/dataclass/eml220/award_type.py
emllib/dataclass/eml220/band_type.py
emllib/dataclass/eml220/binary_raster_format_row_column_orientation.py
emllib/dataclass/eml220/book.py
emllib/dataclass/eml220/cardinality_child_occurances_type_value.py
emllib/dataclass/eml220/cardinality_parent_occurences.py
emllib/dataclass/eml220/cell_geometry_type.py
emllib/dataclass/eml220/chapter.py
emllib/dataclass/eml220/citation.py
emllib/dataclass/eml220/citation_list_type.py
emllib/dataclass/eml220/conference_proceedings.py
emllib/dataclass/eml220/connection_definition_type.py
emllib/dataclass/eml220/connection_type.py
emllib/dataclass/eml220/constraint_type.py
emllib/dataclass/eml220/control_point_point_in_pixel.py
emllib/dataclass/eml220/corner_point_point_in_pixel.py
emllib/dataclass/eml220/data_quality_1.py
emllib/dataclass/eml220/data_quality_2.py
emllib/dataclass/eml220/data_table.py
emllib/dataclass/eml220/data_table_type_case_sensitive.py
emllib/dataclass/eml220/dataset.py
emllib/dataclass/eml220/date_time_domain_type.py
emllib/dataclass/eml220/dependency.py
emllib/dataclass/eml220/dependency_type.py
emllib/dataclass/eml220/description.py
emllib/dataclass/eml220/descriptor_type_value.py
emllib/dataclass/eml220/distribution_type.py
emllib/dataclass/eml220/eml.py
emllib/dataclass/eml220/enumerated_domain_enforced.py
pyemllib-0.2.0.dist-info/LICENSE
pyemllib-0.2.0.dist-info/WHEEL
pyemllib-0.2.0.dist-info/METADATA
pyemllib-0.2.0.dist-info/RECORD
