Metadata-Version: 2.1
Name: pyemllib
Version: 0.2.0
Summary: Python lib to deal with EML (Ecological Metadata Language)
Home-page: https://github.com/jusana/pyemllib
Author: Julien Sananikone
Author-email: julien.sananikone@mnhn.fr
Requires-Python: >=3.8,<=3.11
Classifier: Programming Language :: Python :: 3
Classifier: Programming Language :: Python :: 3.8
Classifier: Programming Language :: Python :: 3.9
Classifier: Programming Language :: Python :: 3.10
Classifier: Programming Language :: Python :: 3.11
Requires-Dist: mdutils (>=1.4.0,<2.0.0)
Requires-Dist: xsdata[lxml] (==22.9)
Project-URL: Documentation, https://jusana.github.io/pyemllib/
Project-URL: Repository, https://github.com/jusana/pyemllib
